nomad_camels_driver_cam_control_pylablib/cam_control_pylablib.py
nomad_camels_driver_cam_control_pylablib/cam_control_pylablib_ophyd.py
nomad_camels_driver_cam_control_pylablib-0.1.4.dist-info/LICENSE.txt
nomad_camels_driver_cam_control_pylablib-0.1.4.dist-info/METADATA
nomad_camels_driver_cam_control_pylablib-0.1.4.dist-info/WHEEL
nomad_camels_driver_cam_control_pylablib-0.1.4.dist-info/top_level.txt
nomad_camels_driver_cam_control_pylablib-0.1.4.dist-info/RECORD
